<?xml version="1.0" encoding="utf-8" standalone="yes"?>
<Parameters>
  <Connection>
    <DeviceParameters>/IF=tcpip /LOPO=11159 /SA=1</DeviceParameters>
    <ConnectionParameters>/COMT=2500 /RT=1000 /AM=* /SDT=5 /DAIP=10.0.0.50 /REPO=11159 /ANSL=1 /PT=11169</ConnectionParameters>
  </Connection>
  <AsProject>
    <ApjFullFileName>C:\Users\andre\Documents\GitHub\Drawing-robot-semester-1\robot_control\robot_control.apj</ApjFullFileName>
    <ProjectName>robot_control</ProjectName>
    <ActiveConfigurationName>Config1</ActiveConfigurationName>
    <LicenseDataFolder>C:\Users\andre\Documents\GitHub\Drawing-robot-semester-1\robot_control\Temp\Objects\Config1\X20CP1382</LicenseDataFolder>
  </AsProject>
  <General>
    <DeleteParameterFile>false</DeleteParameterFile>
  </General>
</Parameters>